{
  "artists": [
    {
      "id": "ask",
      "name": "@ask",
      "category": "illustrator",
      "subcategory": "Pixiv热门",
      "priority": 2,
      "reviewed": true
    },
    {
      "id": "anmi",
      "name": "@anmi",
      "category": "illustrator",
      "subcategory": "Pixiv热门",
      "priority": 2,
      "reviewed": true
    },
    {
      "id": "fuzichoco",
      "name": "@fuzichoco",
      "category": "illustrator",
      "subcategory": "Pixiv热门",
      "priority": 2,
      "reviewed": true
    },
    {
      "id": "rurudo",
      "name": "@rurudo",
      "category": "illustrator",
      "subcategory": "Pixiv热门",
      "priority": 2,
      "reviewed": true
    },
    {
      "id": "yoneyama_mai",
      "name": "@yoneyama mai",
      "category": "illustrator",
      "subcategory": "Pixiv热门",
      "priority": 2,
      "reviewed": true
    },
    {
      "id": "miv4t",
      "name": "@miv4t",
      "category": "illustrator",
      "subcategory": "Pixiv热门",
      "priority": 1
    },
    {
      "id": "hiten",
      "name": "@hiten",
      "category": "illustrator",
      "subcategory": "Pixiv热门",
      "priority": 2,
      "reviewed": true
    },
    {
      "id": "swav",
      "name": "@swav",
      "category": "illustrator",
      "subcategory": "Pixiv热门",
      "priority": 1
    },
    {
      "id": "rella",
      "name": "@rella",
      "category": "illustrator",
      "subcategory": "Pixiv热门",
      "priority": 2,
      "reviewed": true
    },
    {
      "id": "liduke",
      "name": "@liduke",
      "category": "illustrator",
      "subcategory": "Pixiv热门",
      "priority": 2,
      "reviewed": true
    },
    {
      "id": "hou",
      "name": "@hou",
      "category": "illustrator",
      "subcategory": "Pixiv热门",
      "priority": 1
    },
    {
      "id": "torino_aqua",
      "name": "@torino aqua",
      "category": "illustrator",
      "subcategory": "Pixiv热门",
      "priority": 1
    },
    {
      "id": "azuuru",
      "name": "@azuuru",
      "category": "illustrator",
      "subcategory": "Pixiv热门",
      "priority": 1
    },
    {
      "id": "kantoku",
      "name": "@kantoku",
      "category": "illustrator",
      "subcategory": "Pixiv热门",
      "priority": 1
    },
    {
      "id": "abec",
      "name": "@abec",
      "category": "illustrator",
      "subcategory": "Pixiv热门",
      "priority": 2,
      "reviewed": true
    },
    {
      "id": "tony",
      "name": "@tony",
      "category": "illustrator",
      "subcategory": "Pixiv热门",
      "priority": 1
    },
    {
      "id": "keeggy",
      "name": "@keeggy",
      "category": "illustrator",
      "subcategory": "Pixiv热门",
      "priority": 1
    },
    {
      "id": "guweiz",
      "name": "@guweiz",
      "category": "illustrator",
      "subcategory": "Pixiv热门",
      "priority": 1
    },
    {
      "id": "rosu",
      "name": "@rosu",
      "category": "illustrator",
      "subcategory": "Pixiv热门",
      "priority": 2,
      "reviewed": true
    },
    {
      "id": "kawacy",
      "name": "@kawacy",
      "category": "illustrator",
      "subcategory": "Pixiv热门",
      "priority": 1
    },
    {
      "id": "hews",
      "name": "@hews",
      "category": "illustrator",
      "subcategory": "Pixiv热门",
      "priority": 1
    },
    {
      "id": "hxxg",
      "name": "@hxxg",
      "category": "illustrator",
      "subcategory": "Pixiv热门",
      "priority": 1
    },
    {
      "id": "shiratama",
      "name": "@shiratama",
      "category": "illustrator",
      "subcategory": "萌系",
      "priority": 2,
      "reviewed": true
    },
    {
      "id": "itou_life",
      "name": "@itou life",
      "category": "illustrator",
      "subcategory": "萌系",
      "priority": 1
    },
    {
      "id": "nababa",
      "name": "@nababa",
      "category": "illustrator",
      "subcategory": "萌系",
      "priority": 1
    },
    {
      "id": "hamada_yoshikadu",
      "name": "@hamada yoshikadu",
      "category": "illustrator",
      "subcategory": "萌系",
      "priority": 1
    },
    {
      "id": "tsurusaki_takahiro",
      "name": "@tsurusaki takahiro",
      "category": "illustrator",
      "subcategory": "萌系",
      "priority": 1
    },
    {
      "id": "tiv",
      "name": "@tiv",
      "category": "illustrator",
      "subcategory": "萌系",
      "priority": 1
    },
    {
      "id": "mignon",
      "name": "@mignon",
      "category": "illustrator",
      "subcategory": "萌系",
      "priority": 2,
      "reviewed": true
    },
    {
      "id": "namori",
      "name": "@namori",
      "category": "illustrator",
      "subcategory": "萌系",
      "priority": 1
    },
    {
      "id": "harayutaka",
      "name": "@harayutaka",
      "category": "illustrator",
      "subcategory": "萌系",
      "priority": 2,
      "reviewed": true
    },
    {
      "id": "gomzi",
      "name": "@gomzi",
      "category": "illustrator",
      "subcategory": "萌系",
      "priority": 2,
      "reviewed": true
    },
    {
      "id": "ganbare_duncan",
      "name": "@ganbare duncan",
      "category": "illustrator",
      "subcategory": "萌系",
      "priority": 1
    },
    {
      "id": "kuroduck",
      "name": "@kuroduck",
      "category": "illustrator",
      "subcategory": "厚涂半写实",
      "priority": 2,
      "reviewed": true
    },
    {
      "id": "hiroki_shiroi",
      "name": "@hiroki shiroi",
      "category": "illustrator",
      "subcategory": "厚涂半写实",
      "priority": 1
    },
    {
      "id": "fumio",
      "name": "@fumio",
      "category": "illustrator",
      "subcategory": "厚涂半写实",
      "priority": 2,
      "reviewed": true
    },
    {
      "id": "suzuhara_yuki",
      "name": "@suzuhara yuki",
      "category": "illustrator",
      "subcategory": "厚涂半写实",
      "priority": 2,
      "reviewed": true
    },
    {
      "id": "soejima_shigenori",
      "name": "@soejima shigenori",
      "category": "illustrator",
      "subcategory": "设计感",
      "priority": 1
    },
    {
      "id": "humikane_shimada",
      "name": "@humikane shimada",
      "category": "illustrator",
      "subcategory": "设计感",
      "priority": 1
    },
    {
      "id": "oyari_ashito",
      "name": "@oyari ashito",
      "category": "illustrator",
      "subcategory": "设计感",
      "priority": 1
    },
    {
      "id": "guraburu",
      "name": "@guraburu",
      "category": "illustrator",
      "subcategory": "设计感",
      "priority": 2,
      "reviewed": true
    },
    {
      "id": "saitom",
      "name": "@saitom",
      "category": "illustrator",
      "subcategory": "设计感",
      "priority": 1
    },
    {
      "id": "kuroboshi_kouhaku",
      "name": "@kuroboshi kouhaku",
      "category": "illustrator",
      "subcategory": "设计感",
      "priority": 1
    },
    {
      "id": "arknights",
      "name": "@arknights style",
      "category": "game",
      "subcategory": "游戏美术",
      "priority": 2,
      "reviewed": true
    },
    {
      "id": "no_artist",
      "name": "",
      "category": "control",
      "subcategory": "对照组",
      "priority": 2,
      "reviewed": true
    },
    {
      "id": "agoto",
      "name": "@agoto",
      "category": "illustrator",
      "subcategory": "Pixiv热门",
      "priority": 1
    },
    {
      "id": "loundraw",
      "name": "@loundraw",
      "category": "illustrator",
      "subcategory": "Pixiv热门",
      "priority": 1
    },
    {
      "id": "redjuice",
      "name": "@redjuice",
      "category": "illustrator",
      "subcategory": "Pixiv热门",
      "priority": 1
    },
    {
      "id": "vofan",
      "name": "@vofan",
      "category": "illustrator",
      "subcategory": "Pixiv热门",
      "priority": 1
    },
    {
      "id": "siu",
      "name": "@siu",
      "category": "illustrator",
      "subcategory": "Pixiv热门",
      "priority": 1
    },
    {
      "id": "dora",
      "name": "@dora",
      "category": "illustrator",
      "subcategory": "Pixiv热门",
      "priority": 1
    },
    {
      "id": "hakusai",
      "name": "@hakusai",
      "category": "illustrator",
      "subcategory": "Pixiv热门",
      "priority": 1
    },
    {
      "id": "cait",
      "name": "@cait",
      "category": "illustrator",
      "subcategory": "Pixiv热门",
      "priority": 1
    },
    {
      "id": "kairi",
      "name": "@kairi",
      "category": "illustrator",
      "subcategory": "Pixiv热门",
      "priority": 1
    },
    {
      "id": "kase",
      "name": "@kase",
      "category": "illustrator",
      "subcategory": "Pixiv热门",
      "priority": 1
    },
    {
      "id": "greem",
      "name": "@greem",
      "category": "illustrator",
      "subcategory": "Pixiv热门",
      "priority": 1
    },
    {
      "id": "laejjo",
      "name": "@laejjo",
      "category": "illustrator",
      "subcategory": "Pixiv热门",
      "priority": 1
    },
    {
      "id": "sunhyun",
      "name": "@sunhyun",
      "category": "illustrator",
      "subcategory": "Pixiv热门",
      "priority": 1
    },
    {
      "id": "kaie",
      "name": "@kaie",
      "category": "illustrator",
      "subcategory": "Pixiv热门",
      "priority": 1
    },
    {
      "id": "tamaki",
      "name": "@tamaki",
      "category": "illustrator",
      "subcategory": "Pixiv热门",
      "priority": 1
    },
    {
      "id": "kurione",
      "name": "@kurione",
      "category": "illustrator",
      "subcategory": "Pixiv热门",
      "priority": 1
    }
  ]
}